latticegen/__init__.py
latticegen/_version.py
latticegen/latticegeneration.py
latticegen/singularities.py
latticegen/transformations.py
latticegen-0.0.5.dist-info/LICENSE
latticegen-0.0.5.dist-info/METADATA
latticegen-0.0.5.dist-info/WHEEL
latticegen-0.0.5.dist-info/top_level.txt
latticegen-0.0.5.dist-info/RECORD
