Metadata-Version: 2.1
Name: latticegen
Version: 0.0.5
Summary: A small package to create images of atomic lattices
Home-page: https://github.com/TAdejong/moire-lattice-generator
Author: T.A. de Jong
Author-email: tobiasadejong@gmail.com
License: UNKNOWN
Platform: UNKNOWN
Classifier: Programming Language :: Python :: 3
Classifier: License :: OSI Approved :: MIT License
Classifier: Operating System :: OS Independent
Classifier: Topic :: Scientific/Engineering
Requires-Python: >=3.7
Requires-Dist: numpy
Requires-Dist: dask[array]
Requires-Dist: scikit-image
